azure/mgmt/msi/__init__.py
azure/mgmt/msi/_configuration.py
azure/mgmt/msi/_managed_service_identity_client.py
azure/mgmt/msi/_patch.py
azure/mgmt/msi/_version.py
azure/mgmt/msi/models.py
azure/mgmt/msi/py.typed
azure/mgmt/msi/aio/__init__.py
azure/mgmt/msi/aio/_configuration.py
azure/mgmt/msi/aio/_managed_service_identity_client.py
azure/mgmt/msi/v2018_11_30/__init__.py
azure/mgmt/msi/v2018_11_30/_configuration.py
azure/mgmt/msi/v2018_11_30/_managed_service_identity_client.py
azure/mgmt/msi/v2018_11_30/_patch.py
azure/mgmt/msi/v2018_11_30/_vendor.py
azure/mgmt/msi/v2018_11_30/_version.py
azure/mgmt/msi/v2018_11_30/aio/__init__.py
azure/mgmt/msi/v2018_11_30/aio/_configuration.py
azure/mgmt/msi/v2018_11_30/aio/_managed_service_identity_client.py
azure/mgmt/msi/v2018_11_30/aio/_patch.py
azure/mgmt/msi/v2018_11_30/aio/operations/__init__.py
azure/mgmt/msi/v2018_11_30/aio/operations/_operations.py
azure/mgmt/msi/v2018_11_30/aio/operations/_patch.py
azure/mgmt/msi/v2018_11_30/aio/operations/_system_assigned_identities_operations.py
azure/mgmt/msi/v2018_11_30/aio/operations/_user_assigned_identities_operations.py
azure/mgmt/msi/v2018_11_30/models/__init__.py
azure/mgmt/msi/v2018_11_30/models/_models_py3.py
azure/mgmt/msi/v2018_11_30/models/_patch.py
azure/mgmt/msi/v2018_11_30/operations/__init__.py
azure/mgmt/msi/v2018_11_30/operations/_operations.py
azure/mgmt/msi/v2018_11_30/operations/_patch.py
azure/mgmt/msi/v2018_11_30/operations/_system_assigned_identities_operations.py
azure/mgmt/msi/v2018_11_30/operations/_user_assigned_identities_operations.py
azure/mgmt/msi/v2021_09_30_preview/__init__.py
azure/mgmt/msi/v2021_09_30_preview/_configuration.py
azure/mgmt/msi/v2021_09_30_preview/_managed_service_identity_client.py
azure/mgmt/msi/v2021_09_30_preview/_patch.py
azure/mgmt/msi/v2021_09_30_preview/_vendor.py
azure/mgmt/msi/v2021_09_30_preview/_version.py
azure/mgmt/msi/v2021_09_30_preview/aio/__init__.py
azure/mgmt/msi/v2021_09_30_preview/aio/_configuration.py
azure_mgmt_msi-6.1.0.dist-info/LICENSE
azure_mgmt_msi-6.1.0.dist-info/METADATA
azure_mgmt_msi-6.1.0.dist-info/WHEEL
azure_mgmt_msi-6.1.0.dist-info/top_level.txt
azure_mgmt_msi-6.1.0.dist-info/RECORD
